MANIFEST.in
README.rst
setup.py
funny_greeting/__init__.py
funny_greeting/text.py
funny_greeting.egg-info/PKG-INFO
funny_greeting.egg-info/SOURCES.txt
funny_greeting.egg-info/dependency_links.txt
funny_greeting.egg-info/not-zip-safe
funny_greeting.egg-info/top_level.txt