Metadata-Version: 1.0
Name: funny-greeting
Version: 0.2
Summary: Greeting in Israeli
Home-page: http://github.com/xuanminhacsi/funny_greeting
Author: Minh Vu
Author-email: xuanminh12995@gmail.com
License: MIT
Platform: UNKNOWN
